campo_estatico_mdf/__init__.py
campo_estatico_mdf/solver.py
campo_estatico_mdf-1.0.2.dist-info/licenses/LICENSE
campo_estatico_mdf-1.0.2.dist-info/METADATA
campo_estatico_mdf-1.0.2.dist-info/WHEEL
campo_estatico_mdf-1.0.2.dist-info/top_level.txt
campo_estatico_mdf-1.0.2.dist-info/RECORD
