Metadata-Version: 2.4
Name: campo-estatico-mdf
Version: 1.0.2
Summary: Simulador 2D del campo electrostático por método de diferencias finitas (Jacobi / Gauss-Seidel).
Author-email: Daniel Criollo <boltzmannmachine0@gmail.com>
License: MIT
Project-URL: Homepage, https://github.com/SanCriolloB/campo-estatico-mdf
Project-URL: Documentation, https://sancriollob.github.io/campo-estatico-mdf/
Project-URL: Issues, https://github.com/SanCriolloB/campo-estatico-mdf/issues
Keywords: electrostatics,finite differences,Jacobi,Gauss-Seidel,numerical methods
Classifier: Development Status :: 5 - Production/Stable
Classifier: Intended Audience :: Science/Research
Classifier: License :: OSI Approved :: MIT License
Classifier: Programming Language :: Python :: 3.9
Classifier: Programming Language :: Python :: 3.10
Classifier: Topic :: Scientific/Engineering :: Physics
Requires-Python: >=3.9
License-File: LICENSE
Requires-Dist: numpy>=1.22
Dynamic: license-file
